cetto
